data/__init__.py
docs/__init__.py
docs/information.py
euler/__init__.py
euler/edge_node.py
euler/graph_api.py
euler/knowlegde_graphy.py
euler/query_engine.py
euler/query_executor.py
euler/query_parser.py
euler/relationship.py
euler/experimental/__init__.py
euler/experimental/text_data_processing.py
euler/functional_tools/__init__.py
euler/functional_tools/aggregation.py
euler/functional_tools/where_statement.py
euler/graph_embedding/__init__.py
euler/graph_embedding/gat_embedd.py
euler/graph_embedding/hash_gnn.py
euler/graph_embedding/node2vec.py
euler/llm_reader/__init__.py
euler/llm_reader/base_llm_reader.py
euler/llm_reader/google_gemini_reader.py
euler/llm_reader/huggingface_reader.py
euler/llm_reader/llm_factory_reader.py
euler/llm_reader/openai_reader.py
euler/path_finding/__init__.py
euler/path_finding/base_pathfinder.py
euler/path_finding/dijakstra_pathfinder.py
euler/similarity/__init__.py
euler/similarity/node_similarity.py
examples/__init__.py
examples/example_usage.py
gui/__init__.py
gui/app.py
gui/gui_navbar.py
gui/modal_dialog.py
gui/syntax_highlighter.py
gui/base64_images/__init__.py
gui/base64_images/exit_base64.py
gui/base64_images/logo_base64.py
gui/base64_images/open_base64.py
gui/base64_images/save_base64.py
gui/base64_images/save_query_base64.py
gui/base64_images/visual_base64.py
gui/fonts/fa-solid-900.ttf
icons/__init__.py
tests/__init__.py
tests/backup_query_parser.py
tests/query_rel_test.py
tests/test_design.py
euler_database-3.0.0.dist-info/METADATA
euler_database-3.0.0.dist-info/WHEEL
euler_database-3.0.0.dist-info/entry_points.txt
euler_database-3.0.0.dist-info/top_level.txt
euler_database-3.0.0.dist-info/RECORD
