Metadata-Version: 2.1
Name: euler_database
Version: 3.0.0
Summary: A graph database application with embedding and similarity calculations.
Author: Prashant Verma
Author-email: prashant27050@gmail.com
Classifier: Programming Language :: Python :: 3
Classifier: License :: OSI Approved :: MIT License
Classifier: Operating System :: OS Independent
Requires-Python: >=3.6
Requires-Dist: numpy
Requires-Dist: scikit-learn
Requires-Dist: torch
Requires-Dist: Pillow
Requires-Dist: customtkinter
Requires-Dist: node2vec
